zero_hid/__init__.py
zero_hid/defaults.py
zero_hid/keyboard.py
zero_hid/mouse.py
zero_hid/hid/__init__.py
zero_hid/hid/keyboard.py
zero_hid/hid/keycodes.py
zero_hid/hid/mouse.py
zero_hid/hid/write.py
zero_hid/keymaps/BE.json
zero_hid/keymaps/BR.json
zero_hid/keymaps/CA.json
zero_hid/keymaps/CH.json
zero_hid/keymaps/CM.json
zero_hid/keymaps/DE_ASCII.json
zero_hid/keymaps/ES.json
zero_hid/keymaps/FI.json
zero_hid/keymaps/FR.json
zero_hid/keymaps/GB.json
zero_hid/keymaps/HE.json
zero_hid/keymaps/IT.json
zero_hid/keymaps/RU.json
zero_hid/keymaps/SV.json
zero_hid/keymaps/US.json
zero_hid/keymaps/__init__.py
zero_hid/keymaps/common.json
zero_hid-1.0.1.dist-info/LICENSE.txt
zero_hid-1.0.1.dist-info/METADATA
zero_hid-1.0.1.dist-info/WHEEL
zero_hid-1.0.1.dist-info/top_level.txt
zero_hid-1.0.1.dist-info/RECORD
