Metadata-Version: 2.1
Name: zero-hid
Version: 1.0.1
Summary: Library for emulate mouse and keyboard on raspberry pi zero
Home-page: https://github.com/thewh1teagle/zero-hid
Download-URL: 
Author: thewh1teagle
Author-email: example@gmail.com
License: LGPL
Keywords: rpi,raspberry,hid
Classifier: Development Status :: 3 - Alpha
Classifier: Intended Audience :: Developers
Classifier: Topic :: Software Development :: Build Tools
Classifier: License :: OSI Approved :: MIT License
Classifier: Programming Language :: Python :: 3.6
Classifier: Programming Language :: Python :: 3.7
Classifier: Programming Language :: Python :: 3.8
License-File: LICENSE.txt
